nanobindgen/__init__.py
nanobindgen/__main__.py
nanobindgen-0.1.0.dist-info/LICENSE
nanobindgen-0.1.0.dist-info/METADATA
nanobindgen-0.1.0.dist-info/WHEEL
nanobindgen-0.1.0.dist-info/top_level.txt
nanobindgen-0.1.0.dist-info/RECORD
