Metadata-Version: 2.2
Name: nanobindgen
Version: 0.1.0
Summary: Automatically generate nanobind bindings.
License: Copyright 2024 Alex Koen
Project-URL: Homepage, https://github.com/pycad-dev/nanobindgen
Classifier: Programming Language :: Python :: 3
Classifier: Operating System :: OS Independent
Requires-Python: >=3.7
License-File: LICENSE
Requires-Dist: tree-sitter==0.21.3
Requires-Dist: tree-sitter-cpp==0.22.3
Requires-Dist: tree-sitter-jsdoc==0.21.0
